niceguiext/__init__.py
niceguiext/form.py
niceguiext/nicecrud.py
niceguiext/nicetable.py
niceguiext/show_error.py
niceguiext/uix.py
niceguiext-0.1.0.dist-info/METADATA
niceguiext-0.1.0.dist-info/WHEEL
niceguiext-0.1.0.dist-info/licenses/LICENSE
niceguiext-0.1.0.dist-info/RECORD
