Metadata-Version: 2.4
Name: niceguiext
Version: 0.1.0
Author-email: wikia <fj.woo@outlook.com>
License-Expression: MIT
License-File: LICENSE
Requires-Python: >=3.11
Requires-Dist: nicegui>=3.3
